pruina/__init__.py
pruina/socket/__init__.py
pruina/socket/client.py
pruina/socket/server.py
pruina/socket/exception/__init__.py
pruina/socket/exception/exception.py
pruina/socket/handler/GeneralHandler.py
pruina/socket/handler/PruinaHandler.py
pruina/socket/handler/__init__.py
pruina/socket/handler/proto/PruinaSocketServer_pb2.py
pruina/socket/handler/proto/__init__.py
pruina/socket/handler/util/__init__.py
pruina/socket/handler/util/util.py
pruina/socket/util/__init__.py
pruina/socket/util/general.py
Pruina_Socket-0.0.5.dist-info/LICENSE
Pruina_Socket-0.0.5.dist-info/METADATA
Pruina_Socket-0.0.5.dist-info/WHEEL
Pruina_Socket-0.0.5.dist-info/top_level.txt
Pruina_Socket-0.0.5.dist-info/RECORD
