Metadata-Version: 2.1
Name: Pruina-Socket
Version: 0.0.5
Summary: Pruina-Socket
Home-page: https://github.com/aminor-z/pruina-socket-python
Author: Aminor_z
Author-email: aminor_z@qq.com
License: MIT
Keywords: pruina socket protobuf server client hook multithreading
Platform: UNKNOWN
Requires-Python: >=3.6
License-File: LICENSE
Requires-Dist: tqdm
Requires-Dist: protobuf
